<methodResponse>
	<params>
		<param>
			<value>
				<struct>
					<member>
						<name>status</name>
						<value>
							<struct>
								<member>
									<name>message</name>
									<value>
										<string>Done</string>
									</value>
								</member>
								<member>
									<name>code</name>
									<value>
										<int>0</int>
									</value>
								</member>
							</struct>
						</value>
					</member>
					<member>
						<name>info</name>
						<value>
							<struct>
								<member>
									<name>memShared</name>
									<value>
										<int>0</int>
									</value>
								</member>
								<member>
									<name>thpState</name>
									<value>
										<string>always</string>
									</value>
								</member>
								<member>
									<name>netConfigDirty</name>
									<value>
										<string>False</string>
									</value>
								</member>
								<member>
									<name>rxRate</name>
									<value>
										<string>0.00</string>
									</value>
								</member>
								<member>
									<name>vmCount</name>
									<value>
										<int>0</int>
									</value>
								</member>
								<member>
									<name>memUsed</name>
									<value>
										<string>17</string>
									</value>
								</member>
								<member>
									<name>storageDomains</name>
									<value>
										<struct>
											<member>
												<name>ac3f03a9-ec72-49bc-8afc-60630ae63e88</name>
												<value>
													<struct>
														<member>
															<name>delay</name>
															<value>
																<string>0.0141088962555</string>
															</value>
														</member>
														<member>
															<name>lastCheck</name>
															<value>
																<string>8.8</string>
															</value>
														</member>
														<member>
															<name>code</name>
															<value>
																<int>0</int>
															</value>
														</member>
														<member>
															<name>valid</name>
															<value>
																<boolean>1</boolean>
															</value>
														</member>
													</struct>
												</value>
											</member>
										</struct>
									</value>
								</member>
								<member>
									<name>network</name>
									<value>
										<struct>
											<member>
												<name>bond4</name>
												<value>
													<struct>
														<member>
															<name>txErrors</name>
															<value>
																<string>0</string>
															</value>
														</member>
														<member>
															<name>state</name>
															<value>
																<string>down</string>
															</value>
														</member>
														<member>
															<name>macAddr</name>
															<value>
																<string></string>
															</value>
														</member>
														<member>
															<name>name</name>
															<value>
																<string>bond4</string>
															</value>
														</member>
														<member>
															<name>txDropped</name>
															<value>
																<string>0</string>
															</value>
														</member>
														<member>
															<name>txRate</name>
															<value>
																<string>0.0</string>
															</value>
														</member>
														<member>
															<name>rxErrors</name>
															<value>
																<string>0</string>
															</value>
														</member>
														<member>
															<name>speed</name>
															<value>
																<string>1000</string>
															</value>
														</member>
														<member>
															<name>rxRate</name>
															<value>
																<string>0.0</string>
															</value>
														</member>
														<member>
															<name>rxDropped</name>
															<value>
																<string>0</string>
															</value>
														</member>
													</struct>
												</value>
											</member>
											<member>
												<name>bond0</name>
												<value>
													<struct>
														<member>
															<name>txErrors</name>
															<value>
																<string>0</string>
															</value>
														</member>
														<member>
															<name>state</name>
															<value>
																<string>down</string>
															</value>
														</member>
														<member>
															<name>macAddr</name>
															<value>
																<string></string>
															</value>
														</member>
														<member>
															<name>name</name>
															<value>
																<string>bond0</string>
															</value>
														</member>
														<member>
															<name>txDropped</name>
															<value>
																<string>0</string>
															</value>
														</member>
														<member>
															<name>txRate</name>
															<value>
																<string>0.0</string>
															</value>
														</member>
														<member>
															<name>rxErrors</name>
															<value>
																<string>0</string>
															</value>
														</member>
														<member>
															<name>speed</name>
															<value>
																<string>1000</string>
															</value>
														</member>
														<member>
															<name>rxRate</name>
															<value>
																<string>0.0</string>
															</value>
														</member>
														<member>
															<name>rxDropped</name>
															<value>
																<string>0</string>
															</value>
														</member>
													</struct>
												</value>
											</member>
											<member>
												<name>bond1</name>
												<value>
													<struct>
														<member>
															<name>txErrors</name>
															<value>
																<string>0</string>
															</value>
														</member>
														<member>
															<name>state</name>
															<value>
																<string>down</string>
															</value>
														</member>
														<member>
															<name>macAddr</name>
															<value>
																<string></string>
															</value>
														</member>
														<member>
															<name>name</name>
															<value>
																<string>bond1</string>
															</value>
														</member>
														<member>
															<name>txDropped</name>
															<value>
																<string>0</string>
															</value>
														</member>
														<member>
															<name>txRate</name>
															<value>
																<string>0.0</string>
															</value>
														</member>
														<member>
															<name>rxErrors</name>
															<value>
																<string>0</string>
															</value>
														</member>
														<member>
															<name>speed</name>
															<value>
																<string>1000</string>
															</value>
														</member>
														<member>
															<name>rxRate</name>
															<value>
																<string>0.0</string>
															</value>
														</member>
														<member>
															<name>rxDropped</name>
															<value>
																<string>0</string>
															</value>
														</member>
													</struct>
												</value>
											</member>
											<member>
												<name>bond2</name>
												<value>
													<struct>
														<member>
															<name>txErrors</name>
															<value>
																<string>0</string>
															</value>
														</member>
														<member>
															<name>state</name>
															<value>
																<string>down</string>
															</value>
														</member>
														<member>
															<name>macAddr</name>
															<value>
																<string></string>
															</value>
														</member>
														<member>
															<name>name</name>
															<value>
																<string>bond2</string>
															</value>
														</member>
														<member>
															<name>txDropped</name>
															<value>
																<string>0</string>
															</value>
														</member>
														<member>
															<name>txRate</name>
															<value>
																<string>0.0</string>
															</value>
														</member>
														<member>
															<name>rxErrors</name>
															<value>
																<string>0</string>
															</value>
														</member>
														<member>
															<name>speed</name>
															<value>
																<string>1000</string>
															</value>
														</member>
														<member>
															<name>rxRate</name>
															<value>
																<string>0.0</string>
															</value>
														</member>
														<member>
															<name>rxDropped</name>
															<value>
																<string>0</string>
															</value>
														</member>
													</struct>
												</value>
											</member>
											<member>
												<name>bond3</name>
												<value>
													<struct>
														<member>
															<name>txErrors</name>
															<value>
																<string>0</string>
															</value>
														</member>
														<member>
															<name>state</name>
															<value>
																<string>down</string>
															</value>
														</member>
														<member>
															<name>macAddr</name>
															<value>
																<string></string>
															</value>
														</member>
														<member>
															<name>name</name>
															<value>
																<string>bond3</string>
															</value>
														</member>
														<member>
															<name>txDropped</name>
															<value>
																<string>0</string>
															</value>
														</member>
														<member>
															<name>txRate</name>
															<value>
																<string>0.0</string>
															</value>
														</member>
														<member>
															<name>rxErrors</name>
															<value>
																<string>0</string>
															</value>
														</member>
														<member>
															<name>speed</name>
															<value>
																<string>1000</string>
															</value>
														</member>
														<member>
															<name>rxRate</name>
															<value>
																<string>0.0</string>
															</value>
														</member>
														<member>
															<name>rxDropped</name>
															<value>
																<string>0</string>
															</value>
														</member>
													</struct>
												</value>
											</member>
											<member>
												<name>em1</name>
												<value>
													<struct>
														<member>
															<name>txErrors</name>
															<value>
																<string>0</string>
															</value>
														</member>
														<member>
															<name>state</name>
															<value>
																<string>up</string>
															</value>
														</member>
														<member>
															<name>macAddr</name>
															<value>
																<string></string>
															</value>
														</member>
														<member>
															<name>name</name>
															<value>
																<string>em1</string>
															</value>
														</member>
														<member>
															<name>txDropped</name>
															<value>
																<string>0</string>
															</value>
														</member>
														<member>
															<name>txRate</name>
															<value>
																<string>0.0</string>
															</value>
														</member>
														<member>
															<name>rxErrors</name>
															<value>
																<string>0</string>
															</value>
														</member>
														<member>
															<name>speed</name>
															<value>
																<string>1000</string>
															</value>
														</member>
														<member>
															<name>rxRate</name>
															<value>
																<string>0.0</string>
															</value>
														</member>
														<member>
															<name>rxDropped</name>
															<value>
																<string>14965</string>
															</value>
														</member>
													</struct>
												</value>
											</member>
											<member>
												<name>em2</name>
												<value>
													<struct>
														<member>
															<name>txErrors</name>
															<value>
																<string>0</string>
															</value>
														</member>
														<member>
															<name>state</name>
															<value>
																<string>down</string>
															</value>
														</member>
														<member>
															<name>macAddr</name>
															<value>
																<string></string>
															</value>
														</member>
														<member>
															<name>name</name>
															<value>
																<string>em2</string>
															</value>
														</member>
														<member>
															<name>txDropped</name>
															<value>
																<string>0</string>
															</value>
														</member>
														<member>
															<name>txRate</name>
															<value>
																<string>0.0</string>
															</value>
														</member>
														<member>
															<name>rxErrors</name>
															<value>
																<string>0</string>
															</value>
														</member>
														<member>
															<name>speed</name>
															<value>
																<string>1000</string>
															</value>
														</member>
														<member>
															<name>rxRate</name>
															<value>
																<string>0.0</string>
															</value>
														</member>
														<member>
															<name>rxDropped</name>
															<value>
																<string>0</string>
															</value>
														</member>
													</struct>
												</value>
											</member>
										</struct>
									</value>
								</member>
								<member>
									<name>txDropped</name>
									<value>
										<string>0</string>
									</value>
								</member>
								<member>
									<name>cpuUser</name>
									<value>
										<string>0.25</string>
									</value>
								</member>
								<member>
									<name>ksmPages</name>
									<value>
										<int>100</int>
									</value>
								</member>
								<member>
									<name>elapsedTime</name>
									<value>
										<string>183256</string>
									</value>
								</member>
								<member>
									<name>cpuLoad</name>
									<value>
										<string>0.02</string>
									</value>
								</member>
								<member>
									<name>cpuSys</name>
									<value>
										<string>0.09</string>
									</value>
								</member>
								<member>
									<name>diskStats</name>
									<value>
										<struct>
											<member>
												<name>/var/log</name>
												<value>
													<struct>
														<member>
															<name>free</name>
															<value>
																<string>44231</string>
															</value>
														</member>
													</struct>
												</value>
											</member>
											<member>
												<name>/var/log/core</name>
												<value>
													<struct>
														<member>
															<name>free</name>
															<value>
																<string>44231</string>
															</value>
														</member>
													</struct>
												</value>
											</member>
											<member>
												<name>/var/run/vdsm/</name>
												<value>
													<struct>
														<member>
															<name>free</name>
															<value>
																<string>3978</string>
															</value>
														</member>
													</struct>
												</value>
											</member>
											<member>
												<name>/tmp</name>
												<value>
													<struct>
														<member>
															<name>free</name>
															<value>
																<string>44231</string>
															</value>
														</member>
													</struct>
												</value>
											</member>
										</struct>
									</value>
								</member>
								<member>
									<name>memCommitted</name>
									<value>
										<int>0</int>
									</value>
								</member>
								<member>
									<name>ksmState</name>
									<value>
										<boolean>0</boolean>
									</value>
								</member>
								<member>
									<name>vmMigrating</name>
									<value>
										<int>0</int>
									</value>
								</member>
								<member>
									<name>ksmCpu</name>
									<value>
										<int>0</int>
									</value>
								</member>
								<member>
									<name>memAvailable</name>
									<value>
										<int>6435</int>
									</value>
								</member>
								<member>
									<name>txRate</name>
									<value>
										<string>0.00</string>
									</value>
								</member>
								<member>
									<name>cpuUserVdsmd</name>
									<value>
										<string>0.50</string>
									</value>
								</member>
								<member>
									<name>momStatus</name>
									<value>
										<string>active</string>
									</value>
								</member>
								<member>
									<name>generationID</name>
									<value>
										<string>28f88125-6e5e-4804-8c5d-b4620f80bc9c</string>
									</value>
								</member>
								<member>
									<name>rxDropped</name>
									<value>
										<string>14965</string>
									</value>
								</member>
								<member>
									<name>swapTotal</name>
									<value>
										<int>20031</int>
									</value>
								</member>
								<member>
									<name>swapFree</name>
									<value>
										<int>20031</int>
									</value>
								</member>
								<member>
									<name>statsAge</name>
									<value>
										<string>0.43</string>
									</value>
								</member>
								<member>
									<name>dateTime</name>
									<value>
										<string>2013-02-10T19:09:11 GMT</string>
									</value>
								</member>
								<member>
									<name>anonHugePages</name>
									<value>
										<string>662</string>
									</value>
								</member>
								<member>
									<name>cpuIdle</name>
									<value>
										<string>99.66</string>
									</value>
								</member>
								<member>
									<name>vmActive</name>
									<value>
										<int>0</int>
									</value>
								</member>
								<member>
									<name>cpuSysVdsmd</name>
									<value>
										<string>0.25</string>
									</value>
								</member>
							</struct>
						</value>
					</member>
				</struct>
			</value>
		</param>
	</params>
</methodResponse>
